{
  "title": "Striver's SDE Sheet - Top Coding Interview Problems",
  "slug": "sde-sheet",
  "description": "SDE Sheet contains handpicked top coding interview questions from different topics of Data Structures & Algorithms. These problems are among the most asked in interviews at Google, Amazon, Microsoft, Facebook, Swiggy, Flipkart, etc., and cover almost all essential DSA concepts.",
  "lastUpdated": "2025-12-13",
  "type": "dsa",
  "totalProblems": 191,
  "sections": [
    {
      "title": "Arrays",
      "slug": "arrays",
      "order": 1,
      "problems": [
        {
          "title": "Set Matrix Zeroes",
          "slug": "set-matrix-zeroes",
          "difficulty": "Medium",
          "topic": "Arrays",
          "platform": "LeetCode",
          "solveLink": "https://leetcode.com/problems/set-matrix-zeroes/",
          "editorialLink": "https://takeuforward.org/data-structure/set-matrix-zero/",
          "postLink": "https://takeuforward.org/data-structure/set-matrix-zero/",
          "youtubeLink": "https://www.youtube.com/watch?v=M65xBewcqcI",
          "isPremium": false,
          "tags": ["matrix", "in-place"]
        },
        {
          "title": "Pascal's Triangle",
          "slug": "pascals-triangle",
          "difficulty": "Easy",
          "topic": "Arrays",
          "platform": "LeetCode",
          "solveLink": "https://leetcode.com/problems/pascals-triangle/",
          "editorialLink": "https://takeuforward.org/data-structure/pascal-triangle/",
          "postLink": "https://takeuforward.org/data-structure/pascal-triangle/",
          "youtubeLink": "https://www.youtube.com/watch?v=6FLvhQjZqvM",
          "isPremium": false,
          "tags": ["math", "arrays"]
        },
        {
          "title": "Next Permutation",
          "slug": "next-permutation",
          "difficulty": "Medium",
          "topic": "Arrays",
          "platform": "LeetCode",
          "solveLink": "https://leetcode.com/problems/next-permutation/",
          "editorialLink": "https://takeuforward.org/data-structure/next-permutation/",
          "postLink": "https://takeuforward.org/data-structure/next-permutation/",
          "youtubeLink": "https://www.youtube.com/watch?v=LuLCLgMElus",
          "isPremium": false,
          "tags": ["math", "permutations"]
        },
        {
          "title": "Kadane's Algorithm",
          "slug": "kadane-algorithm",
          "difficulty": "Medium",
          "topic": "Arrays",
          "platform": "GeeksForGeeks",
          "solveLink": "https://practice.geeksforgeeks.org/problems/kadanes-algorithm/0",
          "editorialLink": "https://takeuforward.org/data-structure/kadanes-algorithm/",
          "postLink": "https://takeuforward.org/data-structure/kadanes-algorithm/",
          "youtubeLink": "https://www.youtube.com/watch?v=AHZpyENo7k4",
          "isPremium": false,
          "tags": ["dp", "subarray"]
        },
        {
          "title": "Sort an array of 0's 1's and 2's",
          "slug": "sort-0-1-2",
          "difficulty": "Medium",
          "topic": "Arrays",
          "platform": "LeetCode",
          "solveLink": "https://leetcode.com/problems/sort-colors/",
          "editorialLink": "https://takeuforward.org/data-structure/sort-an-array-of-0s-1s-and-2s/",
          "postLink": "https://takeuforward.org/data-structure/sort-an-array-of-0s-1s-and-2s/",
          "youtubeLink": "https://www.youtube.com/watch?v=oaVa-9wmpns",
          "isPremium": false,
          "tags": ["two-pointers", "sorting"]
        },
        {
          "title": "Stock Buy and Sell",
          "slug": "stock-buy-and-sell",
          "difficulty": "Medium",
          "topic": "Arrays",
          "platform": "LeetCode",
          "solveLink": "https://leetcode.com/problems/best-time-to-buy-and-sell-stock/",
          "editorialLink": "https://takeuforward.org/data-structure/stock-buy-and-sell/",
          "postLink": "https://takeuforward.org/data-structure/stock-buy-and-sell/",
          "youtubeLink": "https://www.youtube.com/watch?v=eMSfBgbiEjk",
          "isPremium": false,
          "tags": ["arrays", "greedy"]
        }
      ]
    },
    {
      "title": "Arrays Part-II",
      "slug": "arrays-part-2",
      "order": 2,
      "problems": [
        {
          "title": "Rotate Matrix by 90 Degrees",
          "slug": "rotate-matrix-90",
          "difficulty": "Medium",
          "topic": "Arrays",
          "platform": "LeetCode",
          "solveLink": "https://leetcode.com/problems/rotate-image/",
          "editorialLink": "https://takeuforward.org/data-structure/rotate-image/",
          "postLink": "https://takeuforward.org/data-structure/rotate-image/",
          "youtubeLink": "https://www.youtube.com/watch?v=Y72QeX0Efxw",
          "isPremium": false,
          "tags": ["matrix", "in-place"]
        },
        {
          "title": "Merge Overlapping Subintervals",
          "slug": "merge-intervals",
          "difficulty": "Medium",
          "topic": "Arrays",
          "platform": "LeetCode",
          "solveLink": "https://leetcode.com/problems/merge-intervals/",
          "editorialLink": "https://takeuforward.org/data-structure/merge-overlapping-subintervals/",
          "postLink": "https://takeuforward.org/data-structure/merge-overlapping-subintervals/",
          "youtubeLink": "https://www.youtube.com/watch?v=2JzRBPFYbKE",
          "isPremium": false,
          "tags": ["intervals", "sorting"]
        },
        {
          "title": "Merge Two Sorted Arrays Without Extra Space",
          "slug": "merge-two-sorted-arrays-without-extra-space",
          "difficulty": "Medium",
          "topic": "Arrays",
          "platform": "GeeksForGeeks",
          "solveLink": "https://practice.geeksforgeeks.org/problems/merge-two-sorted-arrays/0",
          "editorialLink": "https://takeuforward.org/data-structure/merge-two-sorted-arrays-without-extra-space/",
          "postLink": "https://takeuforward.org/data-structure/merge-two-sorted-arrays-without-extra-space/",
          "youtubeLink": "https://www.youtube.com/watch?v=hVl2b3bLzBw",
          "isPremium": false,
          "tags": ["arrays", "two-pointers"]
        },
        {
          "title": "Find the Duplicate Number",
          "slug": "find-duplicate-number",
          "difficulty": "Medium",
          "topic": "Arrays",
          "platform": "LeetCode",
          "solveLink": "https://leetcode.com/problems/find-the-duplicate-number/",
          "editorialLink": "https://takeuforward.org/data-structure/find-the-duplicate-number/",
          "postLink": "https://takeuforward.org/data-structure/find-the-duplicate-number/",
          "youtubeLink": "https://www.youtube.com/watch?v=32Ll35mhWg0",
          "isPremium": false,
          "tags": ["cycle-detection", "arrays"]
        },
        {
          "title": "Find the Repeating and Missing Number",
          "slug": "find-repeating-and-missing-number",
          "difficulty": "Hard",
          "topic": "Arrays",
          "platform": "GeeksForGeeks",
          "solveLink": "https://practice.geeksforgeeks.org/problems/find-missing-and-repeating/0",
          "editorialLink": "https://takeuforward.org/data-structure/find-the-repeating-and-missing-number/",
          "postLink": "https://takeuforward.org/data-structure/find-the-repeating-and-missing-number/",
          "youtubeLink": "https://www.youtube.com/watch?v=1kZq4A9yPqc",
          "isPremium": false,
          "tags": ["math", "bit-manipulation"]
        },
        {
          "title": "Inversion of Array (Merge Sort)",
          "slug": "count-inversions",
          "difficulty": "Hard",
          "topic": "Arrays",
          "platform": "GeeksForGeeks",
          "solveLink": "https://practice.geeksforgeeks.org/problems/inversion-of-array/0",
          "editorialLink": "https://takeuforward.org/data-structure/count-inversions/",
          "postLink": "https://takeuforward.org/data-structure/count-inversions/",
          "youtubeLink": "https://www.youtube.com/watch?v=kQ1mJlwW-c0",
          "isPremium": false,
          "tags": ["merge-sort", "divide-and-conquer"]
        }
      ]
    },
    {
      "title": "Arrays Part-III",
      "slug": "arrays-part-3",
      "order": 3,
      "problems": [
        {
          "title": "Search in a 2D Matrix",
          "slug": "search-2d-matrix",
          "difficulty": "Hard",
          "topic": "Arrays",
          "platform": "LeetCode",
          "solveLink": "https://leetcode.com/problems/search-a-2d-matrix/",
          "editorialLink": "https://takeuforward.org/data-structure/search-in-a-2d-matrix/",
          "postLink": "https://takeuforward.org/data-structure/search-in-a-2d-matrix/",
          "youtubeLink": "https://www.youtube.com/watch?v=ZYpYur0znng",
          "isPremium": false,
          "tags": ["binary-search", "matrix"]
        },
        {
          "title": "Pow(x, n)",
          "slug": "pow-x-n",
          "difficulty": "Easy",
          "topic": "Arrays",
          "platform": "LeetCode",
          "solveLink": "https://leetcode.com/problems/powx-n/",
          "editorialLink": "https://takeuforward.org/data-structure/implement-powxn/",
          "postLink": "https://takeuforward.org/data-structure/implement-powxn/",
          "youtubeLink": "https://www.youtube.com/watch?v=l0YC3876qxg",
          "isPremium": false,
          "tags": ["math", "recursion"]
        },
        {
          "title": "Majority Element-I",
          "slug": "majority-element",
          "difficulty": "Easy",
          "topic": "Arrays",
          "platform": "LeetCode",
          "solveLink": "https://leetcode.com/problems/majority-element/",
          "editorialLink": "https://takeuforward.org/data-structure/find-the-majority-element-that-occurs-more-than-n2-times/",
          "postLink": "https://takeuforward.org/data-structure/find-the-majority-element-that-occurs-more-than-n2-times/",
          "youtubeLink": "https://www.youtube.com/watch?v=nP_ns3uSh80",
          "isPremium": false,
          "tags": ["arrays", "moore-voting"]
        },
        {
          "title": "Majority Element-II",
          "slug": "majority-element-2",
          "difficulty": "Hard",
          "topic": "Arrays",
          "platform": "LeetCode",
          "solveLink": "https://leetcode.com/problems/majority-element-ii/",
          "editorialLink": "https://takeuforward.org/data-structure/majority-element-ii/",
          "postLink": "https://takeuforward.org/data-structure/majority-element-ii/",
          "youtubeLink": "https://www.youtube.com/watch?v=FoYd0g8lq1k",
          "isPremium": false,
          "tags": ["arrays", "moore-voting"]
        },
        {
          "title": "Grid Unique Paths",
          "slug": "unique-paths",
          "difficulty": "Medium",
          "topic": "Arrays",
          "platform": "LeetCode",
          "solveLink": "https://leetcode.com/problems/unique-paths/",
          "editorialLink": "https://takeuforward.org/data-structure/grid-unique-paths/",
          "postLink": "https://takeuforward.org/data-structure/grid-unique-paths/",
          "youtubeLink": "https://www.youtube.com/watch?v=t_f0nwwdg5o",
          "isPremium": false,
          "tags": ["dp", "combinatorics"]
        },
        {
          "title": "Reverse Pairs",
          "slug": "reverse-pairs",
          "difficulty": "Hard",
          "topic": "Arrays",
          "platform": "LeetCode",
          "solveLink": "https://leetcode.com/problems/reverse-pairs/",
          "editorialLink": "https://takeuforward.org/data-structure/reverse-pairs/",
          "postLink": "https://takeuforward.org/data-structure/reverse-pairs/",
          "youtubeLink": "https://www.youtube.com/watch?v=0x3mti4nCzM",
          "isPremium": false,
          "tags": ["merge-sort", "divide-and-conquer"]
        }
      ]
    },
    {
      "title": "Arrays Part-IV",
      "slug": "arrays-part-4",
      "order": 4,
      "problems": [
        {
          "title": "Two Sum",
          "slug": "two-sum",
          "difficulty": "Easy",
          "topic": "Arrays",
          "platform": "LeetCode",
          "solveLink": "https://leetcode.com/problems/two-sum/",
          "editorialLink": "https://takeuforward.org/data-structure/two-sum/",
          "postLink": "https://takeuforward.org/data-structure/two-sum/",
          "youtubeLink": "https://www.youtube.com/watch?v=UXDSeD9mN-k",
          "isPremium": false,
          "tags": ["hashmap", "arrays"]
        },
        {
          "title": "4 Sum",
          "slug": "four-sum",
          "difficulty": "Medium",
          "topic": "Arrays",
          "platform": "LeetCode",
          "solveLink": "https://leetcode.com/problems/4sum/",
          "editorialLink": "https://takeuforward.org/data-structure/4-sum/",
          "postLink": "https://takeuforward.org/data-structure/4-sum/",
          "youtubeLink": "https://www.youtube.com/watch?v=ZzqgA7Kq9hY",
          "isPremium": false,
          "tags": ["two-pointers", "hashmap"]
        },
        {
          "title": "Longest Consecutive Sequence",
          "slug": "longest-consecutive-sequence",
          "difficulty": "Medium",
          "topic": "Arrays",
          "platform": "LeetCode",
          "solveLink": "https://leetcode.com/problems/longest-consecutive-sequence/",
          "editorialLink": "https://takeuforward.org/data-structure/longest-consecutive-sequence/",
          "postLink": "https://takeuforward.org/data-structure/longest-consecutive-sequence/",
          "youtubeLink": "https://www.youtube.com/watch?v=qgizvmgeyUM",
          "isPremium": false,
          "tags": ["hashset", "arrays"]
        },
        {
          "title": "Largest Subarray with K Sum",
          "slug": "largest-subarray-with-k-sum",
          "difficulty": "Medium",
          "topic": "Arrays",
          "platform": "GeeksForGeeks",
          "solveLink": "https://practice.geeksforgeeks.org/problems/largest-subarray-with-0-sum/1",
          "editorialLink": "https://takeuforward.org/data-structure/longest-subarray-with-given-sum-k/",
          "postLink": "https://takeuforward.org/data-structure/longest-subarray-with-given-sum-k/",
          "youtubeLink": "https://www.youtube.com/watch?v=9ZyLjjk536U",
          "isPremium": false,
          "tags": ["hashmap", "prefix-sum"]
        },
        {
          "title": "Count Subarrays with Given XOR K",
          "slug": "count-subarrays-with-xor-k",
          "difficulty": "Hard",
          "topic": "Arrays",
          "platform": "GeeksForGeeks",
          "solveLink": "https://practice.geeksforgeeks.org/problems/count-number-of-subarrays-having-given-xor/0",
          "editorialLink": "https://takeuforward.org/data-structure/count-the-number-of-subarrays-having-given-xor/",
          "postLink": "https://takeuforward.org/data-structure/count-the-number-of-subarrays-having-given-xor/",
          "youtubeLink": "https://www.youtube.com/watch?v=lO9R5CaGRPY",
          "isPremium": false,
          "tags": ["trie", "bit-manipulation"]
        },
        {
          "title": "Longest Substring Without Repeating Characters",
          "slug": "longest-substring-without-repeating-characters",
          "difficulty": "Medium",
          "topic": "Arrays",
          "platform": "LeetCode",
          "solveLink": "https://leetcode.com/problems/longest-substring-without-repeating-characters/",
          "editorialLink": "https://takeuforward.org/data-structure/longest-substring-without-repeating-characters/",
          "postLink": "https://takeuforward.org/data-structure/longest-substring-without-repeating-characters/",
          "youtubeLink": "https://www.youtube.com/watch?v=qtVh-XEpsJo",
          "isPremium": false,
          "tags": ["sliding-window", "strings"]
        }
      ]
    },
    {
      "title": "Linked List",
      "slug": "linked-list",
      "order": 5,
      "problems": [
        {
          "title": "Reverse a Linked List",
          "slug": "reverse-linked-list",
          "difficulty": "Medium",
          "topic": "Linked List",
          "platform": "LeetCode",
          "solveLink": "https://leetcode.com/problems/reverse-linked-list/",
          "editorialLink": "https://takeuforward.org/data-structure/reverse-a-linked-list/",
          "postLink": "https://takeuforward.org/data-structure/reverse-a-linked-list/",
          "youtubeLink": "https://www.youtube.com/watch?v=UgYQvF5c6XU",
          "isPremium": false,
          "tags": ["linked-list", "iteration"]
        },
        {
          "title": "Find Middle of Linked List",
          "slug": "find-middle-of-linked-list",
          "difficulty": "Easy",
          "topic": "Linked List",
          "platform": "LeetCode",
          "solveLink": "https://leetcode.com/problems/middle-of-the-linked-list/",
          "editorialLink": "https://takeuforward.org/data-structure/find-middle-of-linked-list/",
          "postLink": "https://takeuforward.org/data-structure/find-middle-of-linked-list/",
          "youtubeLink": "https://www.youtube.com/watch?v=7LjQ57RqgEc",
          "isPremium": false,
          "tags": ["two-pointers", "linked-list"]
        },
        {
          "title": "Merge Two Sorted Lists",
          "slug": "merge-two-sorted-lists",
          "difficulty": "Easy",
          "topic": "Linked List",
          "platform": "LeetCode",
          "solveLink": "https://leetcode.com/problems/merge-two-sorted-lists/",
          "editorialLink": "https://takeuforward.org/data-structure/merge-two-sorted-linked-lists/",
          "postLink": "https://takeuforward.org/data-structure/merge-two-sorted-linked-lists/",
          "youtubeLink": "https://www.youtube.com/watch?v=Xb4slcp1gZ8",
          "isPremium": false,
          "tags": ["linked-list", "merge"]
        },
        {
          "title": "Remove Nth Node From End of List",
          "slug": "remove-nth-node-from-end-of-list",
          "difficulty": "Medium",
          "topic": "Linked List",
          "platform": "LeetCode",
          "solveLink": "https://leetcode.com/problems/remove-nth-node-from-end-of-list/",
          "editorialLink": "https://takeuforward.org/data-structure/remove-nth-node-from-the-back-of-the-linked-list/",
          "postLink": "https://takeuforward.org/data-structure/remove-nth-node-from-the-back-of-the-linked-list/",
          "youtubeLink": "https://www.youtube.com/watch?v=G7v9mKjT6qo",
          "isPremium": false,
          "tags": ["two-pointers", "linked-list"]
        },
        {
          "title": "Add Two Numbers",
          "slug": "add-two-numbers",
          "difficulty": "Medium",
          "topic": "Linked List",
          "platform": "LeetCode",
          "solveLink": "https://leetcode.com/problems/add-two-numbers/",
          "editorialLink": "https://takeuforward.org/data-structure/add-two-numbers-represented-by-linked-lists/",
          "postLink": "https://takeuforward.org/data-structure/add-two-numbers-represented-by-linked-lists/",
          "youtubeLink": "https://www.youtube.com/watch?v=LbCRtr0Dyp0",
          "isPremium": false,
          "tags": ["linked-list", "math"]
        },
        {
          "title": "Delete Node in a Linked List O(1)",
          "slug": "delete-node-in-a-linked-list-o1",
          "difficulty": "Medium",
          "topic": "Linked List",
          "platform": "LeetCode",
          "solveLink": "https://leetcode.com/problems/delete-node-in-a-linked-list/",
          "editorialLink": "https://takeuforward.org/data-structure/delete-node-in-a-linked-list-o1/",
          "postLink": "https://takeuforward.org/data-structure/delete-node-in-a-linked-list-o1/",
          "youtubeLink": "https://www.youtube.com/watch?v=frcY6-8dY7A",
          "isPremium": false,
          "tags": ["linked-list", "pointer"]
        }
      ]
    },
    {
      "title": "Linked List Part-II",
      "slug": "linked-list-part-2",
      "order": 6,
      "problems": [
        {
          "title": "Find the intersection point of Y Linked Lists",
          "slug": "intersection-of-y-linked-lists",
          "difficulty": "Medium",
          "topic": "Linked List",
          "platform": "LeetCode",
          "solveLink": "https://leetcode.com/problems/intersection-of-two-linked-lists/",
          "editorialLink": "https://takeuforward.org/data-structure/find-intersection-point-of-y-linked-lists/",
          "postLink": "https://takeuforward.org/data-structure/find-intersection-point-of-y-linked-lists/",
          "youtubeLink": "https://www.youtube.com/watch?v=FJ69Xn7cCqY",
          "isPremium": false,
          "tags": ["linked-list", "two-pointers"]
        },
        {
          "title": "Detect a Loop in Linked List",
          "slug": "detect-loop-in-linked-list",
          "difficulty": "Medium",
          "topic": "Linked List",
          "platform": "LeetCode",
          "solveLink": "https://leetcode.com/problems/linked-list-cycle/",
          "editorialLink": "https://takeuforward.org/data-structure/detect-a-loop-in-linked-list/",
          "postLink": "https://takeuforward.org/data-structure/detect-a-loop-in-linked-list/",
          "youtubeLink": "https://www.youtube.com/watch?v=354J83hX7RI",
          "isPremium": false,
          "tags": ["cycle-detection", "linked-list"]
        },
        {
          "title": "Reverse Linked List in Groups of K",
          "slug": "reverse-linked-list-in-k-groups",
          "difficulty": "Hard",
          "topic": "Linked List",
          "platform": "LeetCode",
          "solveLink": "https://leetcode.com/problems/reverse-nodes-in-k-group/",
          "editorialLink": "https://takeuforward.org/data-structure/reverse-linked-list-in-groups-of-size-k/",
          "postLink": "https://takeuforward.org/data-structure/reverse-linked-list-in-groups-of-size-k/",
          "youtubeLink": "https://www.youtube.com/watch?v=Of0HPkk3JgI",
          "isPremium": false,
          "tags": ["linked-list", "recursion"]
        },
        {
          "title": "Check if Linked List is Palindrome",
          "slug": "palindrome-linked-list",
          "difficulty": "Medium",
          "topic": "Linked List",
          "platform": "LeetCode",
          "solveLink": "https://leetcode.com/problems/palindrome-linked-list/",
          "editorialLink": "https://takeuforward.org/data-structure/check-if-linked-list-is-palindrome/",
          "postLink": "https://takeuforward.org/data-structure/check-if-linked-list-is-palindrome/",
          "youtubeLink": "https://www.youtube.com/watch?v=-DtNInqFUXs",
          "isPremium": false,
          "tags": ["linked-list", "two-pointers"]
        },
        {
          "title": "Find the Starting Point of Loop in Linked List",
          "slug": "find-starting-point-of-loop-in-linked-list",
          "difficulty": "Medium",
          "topic": "Linked List",
          "platform": "LeetCode",
          "solveLink": "https://leetcode.com/problems/linked-list-cycle-ii/",
          "editorialLink": "https://takeuforward.org/data-structure/find-starting-point-of-loop-in-linked-list/",
          "postLink": "https://takeuforward.org/data-structure/find-starting-point-of-loop-in-linked-list/",
          "youtubeLink": "https://www.youtube.com/watch?v=VxO1aFSe9xU",
          "isPremium": false,
          "tags": ["cycle-detection", "linked-list"]
        },
        {
          "title": "Flattening of Linked List",
          "slug": "flattening-of-linked-list",
          "difficulty": "Hard",
          "topic": "Linked List",
          "platform": "GeeksForGeeks",
          "solveLink": "https://practice.geeksforgeeks.org/problems/flattening-a-linked-list/1",
          "editorialLink": "https://takeuforward.org/data-structure/flattening-a-linked-list/",
          "postLink": "https://takeuforward.org/data-structure/flattening-a-linked-list/",
          "youtubeLink": "https://www.youtube.com/watch?v=twz2I8F6x5s",
          "isPremium": false,
          "tags": ["linked-list", "merge"]
        }
      ]
    },
    {
      "title": "Linked List and Arrays",
      "slug": "linked-list-and-arrays",
      "order": 7,
      "problems": [
        {
          "title": "Rotate a Linked List",
          "slug": "rotate-linked-list",
          "difficulty": "Hard",
          "topic": "Linked List",
          "platform": "LeetCode",
          "solveLink": "https://leetcode.com/problems/rotate-list/",
          "editorialLink": "https://takeuforward.org/data-structure/rotate-a-linked-list/",
          "postLink": "https://takeuforward.org/data-structure/rotate-a-linked-list/",
          "youtubeLink": "https://www.youtube.com/watch?v=9jclu-uKx74",
          "isPremium": false,
          "tags": ["linked-list", "two-pointers"]
        },
        {
          "title": "Clone a Linked List with Random Pointer",
          "slug": "copy-list-with-random-pointer",
          "difficulty": "Hard",
          "topic": "Linked List",
          "platform": "LeetCode",
          "solveLink": "https://leetcode.com/problems/copy-list-with-random-pointer/",
          "editorialLink": "https://takeuforward.org/data-structure/clone-a-linked-list-with-random-and-next-pointer/",
          "postLink": "https://takeuforward.org/data-structure/clone-a-linked-list-with-random-and-next-pointer/",
          "youtubeLink": "https://www.youtube.com/watch?v=VNf6VynfpdM",
          "isPremium": false,
          "tags": ["linked-list", "hashmap"]
        },
        {
          "title": "3 Sum",
          "slug": "three-sum",
          "difficulty": "Medium",
          "topic": "Arrays",
          "platform": "LeetCode",
          "solveLink": "https://leetcode.com/problems/3sum/",
          "editorialLink": "https://takeuforward.org/data-structure/3-sum/",
          "postLink": "https://takeuforward.org/data-structure/3-sum/",
          "youtubeLink": "https://www.youtube.com/watch?v=onLoX6Nhvmg",
          "isPremium": false,
          "tags": ["two-pointers", "arrays"]
        },
        {
          "title": "Trapping Rain Water",
          "slug": "trapping-rain-water",
          "difficulty": "Hard",
          "topic": "Arrays",
          "platform": "LeetCode",
          "solveLink": "https://leetcode.com/problems/trapping-rain-water/",
          "editorialLink": "https://takeuforward.org/data-structure/trapping-rain-water/",
          "postLink": "https://takeuforward.org/data-structure/trapping-rain-water/",
          "youtubeLink": "https://www.youtube.com/watch?v=m18Hntz4go8",
          "isPremium": false,
          "tags": ["two-pointers", "arrays"]
        },
        {
          "title": "Remove Duplicates from Sorted Array",
          "slug": "remove-duplicates-from-sorted-array",
          "difficulty": "Easy",
          "topic": "Arrays",
          "platform": "LeetCode",
          "solveLink": "https://leetcode.com/problems/remove-duplicates-from-sorted-array/",
          "editorialLink": "https://takeuforward.org/data-structure/remove-duplicates-from-sorted-array/",
          "postLink": "https://takeuforward.org/data-structure/remove-duplicates-from-sorted-array/",
          "youtubeLink": "https://www.youtube.com/watch?v=DEJAZBq0FDA",
          "isPremium": false,
          "tags": ["arrays", "two-pointers"]
        },
        {
          "title": "Maximum Consecutive Ones",
          "slug": "max-consecutive-ones",
          "difficulty": "Easy",
          "topic": "Arrays",
          "platform": "LeetCode",
          "solveLink": "https://leetcode.com/problems/max-consecutive-ones/",
          "editorialLink": "https://takeuforward.org/data-structure/maximum-consecutive-ones/",
          "postLink": "https://takeuforward.org/data-structure/maximum-consecutive-ones/",
          "youtubeLink": "https://www.youtube.com/watch?v=mo33aXK5pZg",
          "isPremium": false,
          "tags": ["arrays", "sliding-window"]
        }
      ]
    },
    {
      "title": "Greedy Algorithm",
      "slug": "greedy-algorithm",
      "order": 8,
      "problems": [
        {
          "title": "N Meetings in One Room",
          "slug": "n-meetings-in-one-room",
          "difficulty": "Medium",
          "topic": "Greedy",
          "platform": "GeeksForGeeks",
          "solveLink": "https://practice.geeksforgeeks.org/problems/n-meetings-in-one-room/1",
          "editorialLink": "https://takeuforward.org/data-structure/n-meetings-in-one-room/",
          "postLink": "https://takeuforward.org/data-structure/n-meetings-in-one-room/",
          "youtubeLink": "https://www.youtube.com/watch?v=II6ziNnub1Q",
          "isPremium": false,
          "tags": ["greedy", "intervals"]
        },
        {
          "title": "Minimum Number of Platforms Required for a Railway",
          "slug": "minimum-platforms",
          "difficulty": "Medium",
          "topic": "Greedy",
          "platform": "GeeksForGeeks",
          "solveLink": "https://practice.geeksforgeeks.org/problems/minimum-platforms-1587115620/1",
          "editorialLink": "https://takeuforward.org/data-structure/minimum-platforms-required-for-a-railway/",
          "postLink": "https://takeuforward.org/data-structure/minimum-platforms-required-for-a-railway/",
          "youtubeLink": "https://www.youtube.com/watch?v=dxVcMDI7vyI",
          "isPremium": false,
          "tags": ["greedy", "scheduling"]
        },
        {
          "title": "Job Sequencing Problem",
          "slug": "job-sequencing-problem",
          "difficulty": "Medium",
          "topic": "Greedy",
          "platform": "GeeksForGeeks",
          "solveLink": "https://practice.geeksforgeeks.org/problems/job-sequencing-problem-1587115620/1",
          "editorialLink": "https://takeuforward.org/data-structure/job-sequencing-problem/",
          "postLink": "https://takeuforward.org/data-structure/job-sequencing-problem/",
          "youtubeLink": "https://www.youtube.com/watch?v=II6ziNnub1Q",
          "isPremium": false,
          "tags": ["greedy", "priority-queue"]
        },
        {
          "title": "Fractional Knapsack",
          "slug": "fractional-knapsack",
          "difficulty": "Medium",
          "topic": "Greedy",
          "platform": "GeeksForGeeks",
          "solveLink": "https://practice.geeksforgeeks.org/problems/fractional-knapsack-1587115620/1",
          "editorialLink": "https://takeuforward.org/data-structure/fractional-knapsack/",
          "postLink": "https://takeuforward.org/data-structure/fractional-knapsack/",
          "youtubeLink": "https://www.youtube.com/watch?v=oTTzNMHM05I",
          "isPremium": false,
          "tags": ["greedy", "sorting"]
        },
        {
          "title": "Minimum Coins",
          "slug": "minimum-coins",
          "difficulty": "Hard",
          "topic": "Greedy",
          "platform": "GeeksForGeeks",
          "solveLink": "https://practice.geeksforgeeks.org/problems/coin-piles/0",
          "editorialLink": "https://takeuforward.org/data-structure/minimum-coins/",
          "postLink": "https://takeuforward.org/data-structure/minimum-coins/",
          "youtubeLink": "https://www.youtube.com/watch?v=HqM3lF7KXNk",
          "isPremium": false,
          "tags": ["greedy", "dp"]
        },
        {
          "title": "Assign Cookies",
          "slug": "assign-cookies",
          "difficulty": "Easy",
          "topic": "Greedy",
          "platform": "LeetCode",
          "solveLink": "https://leetcode.com/problems/assign-cookies/",
          "editorialLink": "https://takeuforward.org/data-structure/assign-cookies/",
          "postLink": "https://takeuforward.org/data-structure/assign-cookies/",
          "youtubeLink": "https://www.youtube.com/watch?v=OwFHRb-H5_k",
          "isPremium": false,
          "tags": ["greedy", "two-pointers"]
        }
      ]
    },
    {
      "title": "Recursion",
      "slug": "recursion",
      "order": 9,
      "problems": [
        {
          "title": "Subset Sums",
          "slug": "subset-sums",
          "difficulty": "Medium",
          "topic": "Recursion",
          "platform": "GeeksForGeeks",
          "solveLink": "https://practice.geeksforgeeks.org/problems/subset-sums2234/1",
          "editorialLink": "https://takeuforward.org/data-structure/subset-sum/",
          "postLink": "https://takeuforward.org/data-structure/subset-sum/",
          "youtubeLink": "https://www.youtube.com/watch?v=rYk7M5c0VTg",
          "isPremium": false,
          "tags": ["recursion", "backtracking"]
        },
        {
          "title": "Subsets II (with duplicates)",
          "slug": "subsets-ii",
          "difficulty": "Medium",
          "topic": "Recursion",
          "platform": "LeetCode",
          "solveLink": "https://leetcode.com/problems/subsets-ii/",
          "editorialLink": "https://takeuforward.org/data-structure/subsets-ii/",
          "postLink": "https://takeuforward.org/data-structure/subsets-ii/",
          "youtubeLink": "https://www.youtube.com/watch?v=RIn3gOkbhQE",
          "isPremium": false,
          "tags": ["recursion", "backtracking"]
        },
        {
          "title": "Combination Sum I",
          "slug": "combination-sum",
          "difficulty": "Medium",
          "topic": "Recursion",
          "platform": "LeetCode",
          "solveLink": "https://leetcode.com/problems/combination-sum/",
          "editorialLink": "https://takeuforward.org/data-structure/combination-sum-i/",
          "postLink": "https://takeuforward.org/data-structure/combination-sum-i/",
          "youtubeLink": "https://www.youtube.com/watch?v=OyZFFqQtu98",
          "isPremium": false,
          "tags": ["recursion", "backtracking"]
        },
        {
          "title": "Combination Sum II",
          "slug": "combination-sum-ii",
          "difficulty": "Medium",
          "topic": "Recursion",
          "platform": "LeetCode",
          "solveLink": "https://leetcode.com/problems/combination-sum-ii/",
          "editorialLink": "https://takeuforward.org/data-structure/combination-sum-ii/",
          "postLink": "https://takeuforward.org/data-structure/combination-sum-ii/",
          "youtubeLink": "https://www.youtube.com/watch?v=G1fRTGRxXU8",
          "isPremium": false,
          "tags": ["recursion", "backtracking"]
        },
        {
          "title": "Palindrome Partitioning",
          "slug": "palindrome-partitioning",
          "difficulty": "Medium",
          "topic": "Recursion",
          "platform": "LeetCode",
          "solveLink": "https://leetcode.com/problems/palindrome-partitioning/",
          "editorialLink": "https://takeuforward.org/data-structure/palindrome-partitioning/",
          "postLink": "https://takeuforward.org/data-structure/palindrome-partitioning/",
          "youtubeLink": "https://www.youtube.com/watch?v=WBgsABoClE0",
          "isPremium": false,
          "tags": ["recursion", "backtracking"]
        },
        {
          "title": "Permutation Sequence",
          "slug": "permutation-sequence",
          "difficulty": "Hard",
          "topic": "Recursion",
          "platform": "LeetCode",
          "solveLink": "https://leetcode.com/problems/permutation-sequence/",
          "editorialLink": "https://takeuforward.org/data-structure/permutation-sequence/",
          "postLink": "https://takeuforward.org/data-structure/permutation-sequence/",
          "youtubeLink": "https://www.youtube.com/watch?v=wT7gcXLYoao",
          "isPremium": false,
          "tags": ["math", "recursion"]
        }
      ]
    },
    {
      "title": "Recursion and Backtracking",
      "slug": "recursion-and-backtracking",
      "order": 10,
      "problems": [
        {
          "title": "Permutations",
          "slug": "permutations",
          "difficulty": "Medium",
          "topic": "Backtracking",
          "platform": "LeetCode",
          "solveLink": "https://leetcode.com/problems/permutations/",
          "editorialLink": "https://takeuforward.org/data-structure/permutations/",
          "postLink": "https://takeuforward.org/data-structure/permutations/",
          "youtubeLink": "https://www.youtube.com/watch?v=f2ic2Rsc9pU",
          "isPremium": false,
          "tags": ["backtracking", "recursion"]
        },
        {
          "title": "N-Queen Problem",
          "slug": "n-queen-problem",
          "difficulty": "Hard",
          "topic": "Backtracking",
          "platform": "LeetCode",
          "solveLink": "https://leetcode.com/problems/n-queens/",
          "editorialLink": "https://takeuforward.org/data-structure/n-queen-problem/",
          "postLink": "https://takeuforward.org/data-structure/n-queen-problem/",
          "youtubeLink": "https://www.youtube.com/watch?v=i05Ju7AftcM",
          "isPremium": false,
          "tags": ["backtracking", "matrix"]
        },
        {
          "title": "Sudoku Solver",
          "slug": "sudoku-solver",
          "difficulty": "Hard",
          "topic": "Backtracking",
          "platform": "LeetCode",
          "solveLink": "https://leetcode.com/problems/sudoku-solver/",
          "editorialLink": "https://takeuforward.org/data-structure/sudoku-solver/",
          "postLink": "https://takeuforward.org/data-structure/sudoku-solver/",
          "youtubeLink": "https://www.youtube.com/watch?v=FWAIf_EVUKE",
          "isPremium": false,
          "tags": ["backtracking", "matrix"]
        },
        {
          "title": "M Coloring Problem",
          "slug": "m-coloring-problem",
          "difficulty": "Hard",
          "topic": "Backtracking",
          "platform": "GeeksForGeeks",
          "solveLink": "https://practice.geeksforgeeks.org/problems/m-coloring-problem/0",
          "editorialLink": "https://takeuforward.org/data-structure/m-coloring-problem/",
          "postLink": "https://takeuforward.org/data-structure/m-coloring-problem/",
          "youtubeLink": "https://www.youtube.com/watch?v=wuVwUK25Rfc",
          "isPremium": false,
          "tags": ["backtracking", "graph"]
        },
        {
          "title": "Rat in a Maze",
          "slug": "rat-in-a-maze",
          "difficulty": "Medium",
          "topic": "Backtracking",
          "platform": "GeeksForGeeks",
          "solveLink": "https://practice.geeksforgeeks.org/problems/rat-in-a-maze-problem/1",
          "editorialLink": "https://takeuforward.org/data-structure/rat-in-a-maze/",
          "postLink": "https://takeuforward.org/data-structure/rat-in-a-maze/",
          "youtubeLink": "https://www.youtube.com/watch?v=bLGZhJlt4y0",
          "isPremium": false,
          "tags": ["backtracking", "matrix"]
        },
        {
          "title": "Word Break (Print all ways)",
          "slug": "word-break",
          "difficulty": "Hard",
          "topic": "Backtracking",
          "platform": "LeetCode",
          "solveLink": "https://leetcode.com/problems/word-break-ii/",
          "editorialLink": "https://takeuforward.org/data-structure/word-break/",
          "postLink": "https://takeuforward.org/data-structure/word-break/",
          "youtubeLink": "https://www.youtube.com/watch?v=th4OcGMlI54",
          "isPremium": false,
          "tags": ["backtracking", "dp"]
        }
      ]
    },
    {
      "title": "Binary Search",
      "slug": "binary-search",
      "order": 11,
      "problems": [
        {
          "title": "Nth Root of M",
          "slug": "nth-root-of-m",
          "difficulty": "Medium",
          "topic": "Binary Search",
          "platform": "GeeksForGeeks",
          "solveLink": "https://practice.geeksforgeeks.org/problems/find-nth-root-of-m/0",
          "editorialLink": "https://takeuforward.org/data-structure/nth-root-of-m/",
          "postLink": "https://takeuforward.org/data-structure/nth-root-of-m/",
          "youtubeLink": "https://www.youtube.com/watch?v=WjpswYrS2nY",
          "isPremium": false,
          "tags": ["binary-search", "math"]
        },
        {
          "title": "Matrix Median",
          "slug": "matrix-median",
          "difficulty": "Hard",
          "topic": "Binary Search",
          "platform": "GeeksForGeeks",
          "solveLink": "https://practice.geeksforgeeks.org/problems/find-median-in-row-wise-sorted-matrix/0",
          "editorialLink": "https://takeuforward.org/data-structure/matrix-median/",
          "postLink": "https://takeuforward.org/data-structure/matrix-median/",
          "youtubeLink": "https://www.youtube.com/watch?v=63fPPOdIr2c",
          "isPremium": false,
          "tags": ["binary-search", "matrix"]
        },
        {
          "title": "Single Element in a Sorted Array",
          "slug": "single-element-in-sorted-array",
          "difficulty": "Medium",
          "topic": "Binary Search",
          "platform": "LeetCode",
          "solveLink": "https://leetcode.com/problems/single-element-in-a-sorted-array/",
          "editorialLink": "https://takeuforward.org/data-structure/single-element-in-a-sorted-array/",
          "postLink": "https://takeuforward.org/data-structure/single-element-in-a-sorted-array/",
          "youtubeLink": "https://www.youtube.com/watch?v=PzszoiY5XMQ",
          "isPremium": false,
          "tags": ["binary-search", "bit-manipulation"]
        },
        {
          "title": "Search in Rotated Sorted Array",
          "slug": "search-in-rotated-sorted-array",
          "difficulty": "Medium",
          "topic": "Binary Search",
          "platform": "LeetCode",
          "solveLink": "https://leetcode.com/problems/search-in-rotated-sorted-array/",
          "editorialLink": "https://takeuforward.org/data-structure/search-in-rotated-sorted-array/",
          "postLink": "https://takeuforward.org/data-structure/search-in-rotated-sorted-array/",
          "youtubeLink": "https://www.youtube.com/watch?v=r3pMQ8-Ad5s",
          "isPremium": false,
          "tags": ["binary-search", "arrays"]
        },
        {
          "title": "Median of Two Sorted Arrays",
          "slug": "median-of-two-sorted-arrays",
          "difficulty": "Hard",
          "topic": "Binary Search",
          "platform": "LeetCode",
          "solveLink": "https://leetcode.com/problems/median-of-two-sorted-arrays/",
          "editorialLink": "https://takeuforward.org/data-structure/median-of-two-sorted-arrays/",
          "postLink": "https://takeuforward.org/data-structure/median-of-two-sorted-arrays/",
          "youtubeLink": "https://www.youtube.com/watch?v=NTop3VTjmxk",
          "isPremium": false,
          "tags": ["binary-search", "divide-and-conquer"]
        },
        {
          "title": "Kth Element of Two Sorted Arrays",
          "slug": "kth-element-of-two-sorted-arrays",
          "difficulty": "Hard",
          "topic": "Binary Search",
          "platform": "GeeksForGeeks",
          "solveLink": "https://practice.geeksforgeeks.org/problems/k-th-element-of-two-sorted-array/0",
          "editorialLink": "https://takeuforward.org/data-structure/k-th-element-of-two-sorted-arrays/",
          "postLink": "https://takeuforward.org/data-structure/k-th-element-of-two-sorted-arrays/",
          "youtubeLink": "https://www.youtube.com/watch?v=nv7F4PiLUzo",
          "isPremium": false,
          "tags": ["binary-search", "arrays"]
        },
        {
          "title": "Allocate Minimum Number of Pages",
          "slug": "allocate-minimum-pages",
          "difficulty": "Hard",
          "topic": "Binary Search",
          "platform": "GeeksForGeeks",
          "solveLink": "https://practice.geeksforgeeks.org/problems/allocate-minimum-number-of-pages/0",
          "editorialLink": "https://takeuforward.org/data-structure/allocate-minimum-number-of-pages/",
          "postLink": "https://takeuforward.org/data-structure/allocate-minimum-number-of-pages/",
          "youtubeLink": "https://www.youtube.com/watch?v=gYmWHvRHu-s",
          "isPremium": false,
          "tags": ["binary-search", "greedy"]
        },
        {
          "title": "Aggressive Cows",
          "slug": "aggressive-cows",
          "difficulty": "Hard",
          "topic": "Binary Search",
          "platform": "SPOJ",
          "solveLink": "https://www.spoj.com/problems/AGGRCOW/",
          "editorialLink": "https://takeuforward.org/data-structure/aggressive-cows/",
          "postLink": "https://takeuforward.org/data-structure/aggressive-cows/",
          "youtubeLink": "https://www.youtube.com/watch?v=wSOfYesTBRk",
          "isPremium": false,
          "tags": ["binary-search", "greedy"]
        }
      ]
    },
    {
      "title": "Binary Tree",
      "slug": "binary-tree",
      "order": 12,
      "problems": [
        {
          "title": "Inorder Traversal",
          "slug": "inorder-traversal",
          "difficulty": "Easy",
          "topic": "Binary Tree",
          "platform": "LeetCode",
          "solveLink": "https://leetcode.com/problems/binary-tree-inorder-traversal/",
          "editorialLink": "https://takeuforward.org/data-structure/inorder-traversal/",
          "postLink": "https://takeuforward.org/data-structure/inorder-traversal/",
          "youtubeLink": "https://www.youtube.com/watch?v=Z_NEgBgbRVI",
          "isPremium": false,
          "tags": ["tree", "dfs"]
        },
        {
          "title": "Preorder Traversal",
          "slug": "preorder-traversal",
          "difficulty": "Easy",
          "topic": "Binary Tree",
          "platform": "LeetCode",
          "solveLink": "https://leetcode.com/problems/binary-tree-preorder-traversal/",
          "editorialLink": "https://takeuforward.org/data-structure/preorder-traversal/",
          "postLink": "https://takeuforward.org/data-structure/preorder-traversal/",
          "youtubeLink": "https://www.youtube.com/watch?v=RlUu72JrOCQ",
          "isPremium": false,
          "tags": ["tree", "dfs"]
        },
        {
          "title": "Postorder Traversal",
          "slug": "postorder-traversal",
          "difficulty": "Easy",
          "topic": "Binary Tree",
          "platform": "LeetCode",
          "solveLink": "https://leetcode.com/problems/binary-tree-postorder-traversal/",
          "editorialLink": "https://takeuforward.org/data-structure/postorder-traversal/",
          "postLink": "https://takeuforward.org/data-structure/postorder-traversal/",
          "youtubeLink": "https://www.youtube.com/watch?v=NzIGLLwZBS8",
          "isPremium": false,
          "tags": ["tree", "dfs"]
        },
        {
          "title": "Morris Inorder Traversal",
          "slug": "morris-inorder-traversal",
          "difficulty": "Hard",
          "topic": "Binary Tree",
          "platform": "LeetCode",
          "solveLink": "https://leetcode.com/problems/binary-tree-inorder-traversal/",
          "editorialLink": "https://takeuforward.org/data-structure/morris-inorder-traversal/",
          "postLink": "https://takeuforward.org/data-structure/morris-inorder-traversal/",
          "youtubeLink": "https://www.youtube.com/watch?v=80Zug6D1_r4",
          "isPremium": false,
          "tags": ["tree", "morris-traversal"]
        },
        {
          "title": "Morris Preorder Traversal",
          "slug": "morris-preorder-traversal",
          "difficulty": "Hard",
          "topic": "Binary Tree",
          "platform": "LeetCode",
          "solveLink": "https://leetcode.com/problems/binary-tree-preorder-traversal/",
          "editorialLink": "https://takeuforward.org/data-structure/morris-preorder-traversal/",
          "postLink": "https://takeuforward.org/data-structure/morris-preorder-traversal/",
          "youtubeLink": "https://www.youtube.com/watch?v=80Zug6D1_r4",
          "isPremium": false,
          "tags": ["tree", "morris-traversal"]
        },
        {
          "title": "Left View of Binary Tree",
          "slug": "left-view",
          "difficulty": "Medium",
          "topic": "Binary Tree",
          "platform": "GeeksForGeeks",
          "solveLink": "https://practice.geeksforgeeks.org/problems/left-view-of-binary-tree/1",
          "editorialLink": "https://takeuforward.org/data-structure/left-view-of-binary-tree/",
          "postLink": "https://takeuforward.org/data-structure/left-view-of-binary-tree/",
          "youtubeLink": "https://www.youtube.com/watch?v=KV4mRzTjlAk",
          "isPremium": false,
          "tags": ["tree", "bfs"]
        },
        {
          "title": "Bottom View of Binary Tree",
          "slug": "bottom-view",
          "difficulty": "Medium",
          "topic": "Binary Tree",
          "platform": "GeeksForGeeks",
          "solveLink": "https://practice.geeksforgeeks.org/problems/bottom-view-of-binary-tree/1",
          "editorialLink": "https://takeuforward.org/data-structure/bottom-view-of-binary-tree/",
          "postLink": "https://takeuforward.org/data-structure/bottom-view-of-binary-tree/",
          "youtubeLink": "https://www.youtube.com/watch?v=0FtVY6I4pB8",
          "isPremium": false,
          "tags": ["tree", "bfs"]
        },
        {
          "title": "Top View of Binary Tree",
          "slug": "top-view",
          "difficulty": "Medium",
          "topic": "Binary Tree",
          "platform": "GeeksForGeeks",
          "solveLink": "https://practice.geeksforgeeks.org/problems/top-view-of-binary-tree/1",
          "editorialLink": "https://takeuforward.org/data-structure/top-view-of-binary-tree/",
          "postLink": "https://takeuforward.org/data-structure/top-view-of-binary-tree/",
          "youtubeLink": "https://www.youtube.com/watch?v=Et9OCDNvJ78",
          "isPremium": false,
          "tags": ["tree", "bfs"]
        },
        {
          "title": "Vertical Order Traversal",
          "slug": "vertical-order-traversal",
          "difficulty": "Hard",
          "topic": "Binary Tree",
          "platform": "LeetCode",
          "solveLink": "https://leetcode.com/problems/vertical-order-traversal-of-a-binary-tree/",
          "editorialLink": "https://takeuforward.org/data-structure/vertical-order-traversal/",
          "postLink": "https://takeuforward.org/data-structure/vertical-order-traversal/",
          "youtubeLink": "https://www.youtube.com/watch?v=q_a6lpbKJdw",
          "isPremium": false,
          "tags": ["tree", "bfs"]
        },
        {
          "title": "Root to Leaf Paths",
          "slug": "root-to-leaf-paths",
          "difficulty": "Medium",
          "topic": "Binary Tree",
          "platform": "GeeksForGeeks",
          "solveLink": "https://practice.geeksforgeeks.org/problems/root-to-leaf-paths/1",
          "editorialLink": "https://takeuforward.org/data-structure/root-to-leaf-paths/",
          "postLink": "https://takeuforward.org/data-structure/root-to-leaf-paths/",
          "youtubeLink": "https://www.youtube.com/watch?v=fmflMqVOC7k",
          "isPremium": false,
          "tags": ["tree", "dfs"]
        },
        {
          "title": "Maximum Width of Binary Tree",
          "slug": "max-width-binary-tree",
          "difficulty": "Medium",
          "topic": "Binary Tree",
          "platform": "LeetCode",
          "solveLink": "https://leetcode.com/problems/maximum-width-of-binary-tree/",
          "editorialLink": "https://takeuforward.org/data-structure/maximum-width-of-binary-tree/",
          "postLink": "https://takeuforward.org/data-structure/maximum-width-of-binary-tree/",
          "youtubeLink": "https://www.youtube.com/watch?v=ZbybYvcVLks",
          "isPremium": false,
          "tags": ["tree", "bfs"]
        }
      ]
    },
    {
      "title": "Binary Tree Part-II",
      "slug": "binary-tree-part-2",
      "order": 13,
      "problems": [
        {
          "title": "Level Order Traversal",
          "slug": "level-order-traversal",
          "difficulty": "Medium",
          "topic": "Binary Tree",
          "platform": "LeetCode",
          "solveLink": "https://leetcode.com/problems/binary-tree-level-order-traversal/",
          "editorialLink": "https://takeuforward.org/data-structure/level-order-traversal/",
          "postLink": "https://takeuforward.org/data-structure/level-order-traversal/",
          "youtubeLink": "https://www.youtube.com/watch?v=EoAsWbO7sqg",
          "isPremium": false,
          "tags": ["tree", "bfs"]
        },
        {
          "title": "Maximum Depth of Binary Tree",
          "slug": "max-depth-binary-tree",
          "difficulty": "Easy",
          "topic": "Binary Tree",
          "platform": "LeetCode",
          "solveLink": "https://leetcode.com/problems/maximum-depth-of-binary-tree/",
          "editorialLink": "https://takeuforward.org/data-structure/maximum-depth-of-binary-tree/",
          "postLink": "https://takeuforward.org/data-structure/maximum-depth-of-binary-tree/",
          "youtubeLink": "https://www.youtube.com/watch?v=eD3tmO66aBA",
          "isPremium": false,
          "tags": ["tree", "dfs"]
        },
        {
          "title": "Diameter of Binary Tree",
          "slug": "diameter-binary-tree",
          "difficulty": "Medium",
          "topic": "Binary Tree",
          "platform": "LeetCode",
          "solveLink": "https://leetcode.com/problems/diameter-of-binary-tree/",
          "editorialLink": "https://takeuforward.org/data-structure/diameter-of-binary-tree/",
          "postLink": "https://takeuforward.org/data-structure/diameter-of-binary-tree/",
          "youtubeLink": "https://www.youtube.com/watch?v=Rezetez59Nk",
          "isPremium": false,
          "tags": ["tree", "dfs"]
        },
        {
          "title": "Check for Balanced Tree",
          "slug": "balanced-binary-tree",
          "difficulty": "Easy",
          "topic": "Binary Tree",
          "platform": "LeetCode",
          "solveLink": "https://leetcode.com/problems/balanced-binary-tree/",
          "editorialLink": "https://takeuforward.org/data-structure/check-for-balanced-tree/",
          "postLink": "https://takeuforward.org/data-structure/check-for-balanced-tree/",
          "youtubeLink": "https://www.youtube.com/watch?v=Yt50Jfbd8Po",
          "isPremium": false,
          "tags": ["tree", "dfs"]
        },
        {
          "title": "Lowest Common Ancestor",
          "slug": "lca-binary-tree",
          "difficulty": "Medium",
          "topic": "Binary Tree",
          "platform": "LeetCode",
          "solveLink": "https://leetcode.com/problems/lowest-common-ancestor-of-a-binary-tree/",
          "editorialLink": "https://takeuforward.org/data-structure/lowest-common-ancestor/",
          "postLink": "https://takeuforward.org/data-structure/lowest-common-ancestor/",
          "youtubeLink": "https://www.youtube.com/watch?v=_-QHfMDde90",
          "isPremium": false,
          "tags": ["tree", "dfs"]
        },
        {
          "title": "Check if Two Trees are Identical",
          "slug": "same-tree",
          "difficulty": "Easy",
          "topic": "Binary Tree",
          "platform": "LeetCode",
          "solveLink": "https://leetcode.com/problems/same-tree/",
          "editorialLink": "https://takeuforward.org/data-structure/check-if-two-trees-are-identical/",
          "postLink": "https://takeuforward.org/data-structure/check-if-two-trees-are-identical/",
          "youtubeLink": "https://www.youtube.com/watch?v=BhuvF_-PWS0",
          "isPremium": false,
          "tags": ["tree", "dfs"]
        },
        {
          "title": "ZigZag Traversal",
          "slug": "zigzag-traversal",
          "difficulty": "Medium",
          "topic": "Binary Tree",
          "platform": "LeetCode",
          "solveLink": "https://leetcode.com/problems/binary-tree-zigzag-level-order-traversal/",
          "editorialLink": "https://takeuforward.org/data-structure/zigzag-traversal/",
          "postLink": "https://takeuforward.org/data-structure/zigzag-traversal/",
          "youtubeLink": "https://www.youtube.com/watch?v=3OXWEdlIGl4",
          "isPremium": false,
          "tags": ["tree", "bfs"]
        },
        {
          "title": "Boundary Traversal",
          "slug": "boundary-traversal",
          "difficulty": "Hard",
          "topic": "Binary Tree",
          "platform": "GeeksForGeeks",
          "solveLink": "https://practice.geeksforgeeks.org/problems/boundary-traversal-of-binary-tree/1",
          "editorialLink": "https://takeuforward.org/data-structure/boundary-traversal/",
          "postLink": "https://takeuforward.org/data-structure/boundary-traversal/",
          "youtubeLink": "https://www.youtube.com/watch?v=0ca1nvR0be4",
          "isPremium": false,
          "tags": ["tree", "dfs"]
        }
      ]
    },
    {
      "title": "Binary Tree Part-III",
      "slug": "binary-tree-part-3",
      "order": 14,
      "problems": [
        {
          "title": "Maximum Path Sum",
          "slug": "max-path-sum",
          "difficulty": "Hard",
          "topic": "Binary Tree",
          "platform": "LeetCode",
          "solveLink": "https://leetcode.com/problems/binary-tree-maximum-path-sum/",
          "editorialLink": "https://takeuforward.org/data-structure/maximum-path-sum/",
          "postLink": "https://takeuforward.org/data-structure/maximum-path-sum/",
          "youtubeLink": "https://www.youtube.com/watch?v=9eeHAaElqEo",
          "isPremium": false,
          "tags": ["tree", "dfs"]
        },
        {
          "title": "Construct Binary Tree from Preorder and Inorder",
          "slug": "construct-tree-from-preorder-inorder",
          "difficulty": "Medium",
          "topic": "Binary Tree",
          "platform": "LeetCode",
          "solveLink": "https://leetcode.com/problems/construct-binary-tree-from-preorder-and-inorder-traversal/",
          "editorialLink": "https://takeuforward.org/data-structure/construct-binary-tree-from-preorder-and-inorder/",
          "postLink": "https://takeuforward.org/data-structure/construct-binary-tree-from-preorder-and-inorder/",
          "youtubeLink": "https://www.youtube.com/watch?v=aZNaLrVebKQ",
          "isPremium": false,
          "tags": ["tree", "recursion"]
        },
        {
          "title": "Construct Binary Tree from Postorder and Inorder",
          "slug": "construct-tree-from-postorder-inorder",
          "difficulty": "Medium",
          "topic": "Binary Tree",
          "platform": "LeetCode",
          "solveLink": "https://leetcode.com/problems/construct-binary-tree-from-inorder-and-postorder-traversal/",
          "editorialLink": "https://takeuforward.org/data-structure/construct-binary-tree-from-postorder-and-inorder/",
          "postLink": "https://takeuforward.org/data-structure/construct-binary-tree-from-postorder-and-inorder/",
          "youtubeLink": "https://www.youtube.com/watch?v=LgLRTaEMRVc",
          "isPremium": false,
          "tags": ["tree", "recursion"]
        },
        {
          "title": "Symmetric Binary Tree",
          "slug": "symmetric-tree",
          "difficulty": "Easy",
          "topic": "Binary Tree",
          "platform": "LeetCode",
          "solveLink": "https://leetcode.com/problems/symmetric-tree/",
          "editorialLink": "https://takeuforward.org/data-structure/symmetric-binary-tree/",
          "postLink": "https://takeuforward.org/data-structure/symmetric-binary-tree/",
          "youtubeLink": "https://www.youtube.com/watch?v=nKggNAiEpBE",
          "isPremium": false,
          "tags": ["tree", "dfs"]
        },
        {
          "title": "Flatten Binary Tree to Linked List",
          "slug": "flatten-binary-tree-to-linked-list",
          "difficulty": "Medium",
          "topic": "Binary Tree",
          "platform": "LeetCode",
          "solveLink": "https://leetcode.com/problems/flatten-binary-tree-to-linked-list/",
          "editorialLink": "https://takeuforward.org/data-structure/flatten-binary-tree-to-linked-list/",
          "postLink": "https://takeuforward.org/data-structure/flatten-binary-tree-to-linked-list/",
          "youtubeLink": "https://www.youtube.com/watch?v=sWf7k1x9XR4",
          "isPremium": false,
          "tags": ["tree", "morris-traversal"]
        },
        {
          "title": "Children Sum Property",
          "slug": "children-sum-property",
          "difficulty": "Medium",
          "topic": "Binary Tree",
          "platform": "GeeksForGeeks",
          "solveLink": "https://practice.geeksforgeeks.org/problems/children-sum-parent/1",
          "editorialLink": "https://takeuforward.org/data-structure/children-sum-property/",
          "postLink": "https://takeuforward.org/data-structure/children-sum-property/",
          "youtubeLink": "https://www.youtube.com/watch?v=fnmisPM6cVo",
          "isPremium": false,
          "tags": ["tree", "dfs"]
        }
      ]
    },
    {
      "title": "Binary Search Tree",
      "slug": "binary-search-tree",
      "order": 15,
      "problems": [
        {
          "title": "Search in BST",
          "slug": "search-in-bst",
          "difficulty": "Easy",
          "topic": "BST",
          "platform": "LeetCode",
          "solveLink": "https://leetcode.com/problems/search-in-a-binary-search-tree/",
          "editorialLink": "https://takeuforward.org/data-structure/search-in-bst/",
          "postLink": "https://takeuforward.org/data-structure/search-in-bst/",
          "youtubeLink": "https://www.youtube.com/watch?v=KcNt6v_56cc",
          "isPremium": false,
          "tags": ["bst", "binary-search"]
        },
        {
          "title": "Construct BST from Preorder",
          "slug": "construct-bst-from-preorder",
          "difficulty": "Medium",
          "topic": "BST",
          "platform": "LeetCode",
          "solveLink": "https://leetcode.com/problems/construct-binary-search-tree-from-preorder-traversal/",
          "editorialLink": "https://takeuforward.org/data-structure/construct-bst-from-preorder/",
          "postLink": "https://takeuforward.org/data-structure/construct-bst-from-preorder/",
          "youtubeLink": "https://www.youtube.com/watch?v=Bexswo4pqZQ",
          "isPremium": false,
          "tags": ["bst", "recursion"]
        },
        {
          "title": "Validate BST",
          "slug": "validate-bst",
          "difficulty": "Medium",
          "topic": "BST",
          "platform": "LeetCode",
          "solveLink": "https://leetcode.com/problems/validate-binary-search-tree/",
          "editorialLink": "https://takeuforward.org/data-structure/validate-bst/",
          "postLink": "https://takeuforward.org/data-structure/validate-bst/",
          "youtubeLink": "https://www.youtube.com/watch?v=f-sj7I5oXEI",
          "isPremium": false,
          "tags": ["bst", "dfs"]
        },
        {
          "title": "LCA in BST",
          "slug": "lca-in-bst",
          "difficulty": "Medium",
          "topic": "BST",
          "platform": "LeetCode",
          "solveLink": "https://leetcode.com/problems/lowest-common-ancestor-of-a-binary-search-tree/",
          "editorialLink": "https://takeuforward.org/data-structure/lca-in-bst/",
          "postLink": "https://takeuforward.org/data-structure/lca-in-bst/",
          "youtubeLink": "https://www.youtube.com/watch?v=gs2LMfuOR9k",
          "isPremium": false,
          "tags": ["bst", "dfs"]
        },
        {
          "title": "Inorder Successor and Predecessor in BST",
          "slug": "inorder-successor-predecessor",
          "difficulty": "Medium",
          "topic": "BST",
          "platform": "GeeksForGeeks",
          "solveLink": "https://practice.geeksforgeeks.org/problems/predecessor-and-successor/1",
          "editorialLink": "https://takeuforward.org/data-structure/inorder-successor-predecessor/",
          "postLink": "https://takeuforward.org/data-structure/inorder-successor-predecessor/",
          "youtubeLink": "https://www.youtube.com/watch?v=SXKAD2svfmI",
          "isPremium": false,
          "tags": ["bst", "dfs"]
        }
      ]
    },
    {
      "title": "Binary Search Tree Part-II",
      "slug": "binary-search-tree-part-2",
      "order": 16,
      "problems": [
        {
          "title": "Floor in BST",
          "slug": "floor-in-bst",
          "difficulty": "Medium",
          "topic": "BST",
          "platform": "GeeksForGeeks",
          "solveLink": "https://practice.geeksforgeeks.org/problems/floor-in-bst/1",
          "editorialLink": "https://takeuforward.org/data-structure/floor-in-bst/",
          "postLink": "https://takeuforward.org/data-structure/floor-in-bst/",
          "youtubeLink": "https://www.youtube.com/watch?v=xm_W1ub-K-w",
          "isPremium": false,
          "tags": ["bst", "binary-search"]
        },
        {
          "title": "Ceil in BST",
          "slug": "ceil-in-bst",
          "difficulty": "Medium",
          "topic": "BST",
          "platform": "GeeksForGeeks",
          "solveLink": "https://practice.geeksforgeeks.org/problems/implementing-ceil-in-bst/1",
          "editorialLink": "https://takeuforward.org/data-structure/ceil-in-bst/",
          "postLink": "https://takeuforward.org/data-structure/ceil-in-bst/",
          "youtubeLink": "https://www.youtube.com/watch?v=KSsk8AhdOZA",
          "isPremium": false,
          "tags": ["bst", "binary-search"]
        },
        {
          "title": "Kth Smallest Element in BST",
          "slug": "kth-smallest-in-bst",
          "difficulty": "Medium",
          "topic": "BST",
          "platform": "LeetCode",
          "solveLink": "https://leetcode.com/problems/kth-smallest-element-in-a-bst/",
          "editorialLink": "https://takeuforward.org/data-structure/kth-smallest-in-bst/",
          "postLink": "https://takeuforward.org/data-structure/kth-smallest-in-bst/",
          "youtubeLink": "https://www.youtube.com/watch?v=9TJYWh0adfk",
          "isPremium": false,
          "tags": ["bst", "dfs"]
        },
        {
          "title": "Two Sum in BST",
          "slug": "two-sum-bst",
          "difficulty": "Easy",
          "topic": "BST",
          "platform": "LeetCode",
          "solveLink": "https://leetcode.com/problems/two-sum-iv-input-is-a-bst/",
          "editorialLink": "https://takeuforward.org/data-structure/two-sum-bst/",
          "postLink": "https://takeuforward.org/data-structure/two-sum-bst/",
          "youtubeLink": "https://www.youtube.com/watch?v=ssL3sHwPeb4",
          "isPremium": false,
          "tags": ["bst", "two-pointers"]
        },
        {
          "title": "BST Iterator",
          "slug": "bst-iterator",
          "difficulty": "Medium",
          "topic": "BST",
          "platform": "LeetCode",
          "solveLink": "https://leetcode.com/problems/binary-search-tree-iterator/",
          "editorialLink": "https://takeuforward.org/data-structure/bst-iterator/",
          "postLink": "https://takeuforward.org/data-structure/bst-iterator/",
          "youtubeLink": "https://www.youtube.com/watch?v=D2jMcmxU4bs",
          "isPremium": false,
          "tags": ["bst", "iterator"]
        },
        {
          "title": "Serialize and Deserialize Binary Tree",
          "slug": "serialize-deserialize-binary-tree",
          "difficulty": "Hard",
          "topic": "BST",
          "platform": "LeetCode",
          "solveLink": "https://leetcode.com/problems/serialize-and-deserialize-binary-tree/",
          "editorialLink": "https://takeuforward.org/data-structure/serialize-deserialize-binary-tree/",
          "postLink": "https://takeuforward.org/data-structure/serialize-deserialize-binary-tree/",
          "youtubeLink": "https://www.youtube.com/watch?v=-YbXySKJsX8",
          "isPremium": false,
          "tags": ["tree", "serialization"]
        }
      ]
    },
    {
      "title": "Graph",
      "slug": "graph",
      "order": 17,
      "problems": [
        {
          "title": "Clone a Graph",
          "slug": "clone-graph",
          "difficulty": "Medium",
          "topic": "Graph",
          "platform": "LeetCode",
          "solveLink": "https://leetcode.com/problems/clone-graph/",
          "editorialLink": "https://takeuforward.org/data-structure/clone-graph/",
          "postLink": "https://takeuforward.org/data-structure/clone-graph/",
          "youtubeLink": "https://www.youtube.com/watch?v=mQeF6bN8hMk",
          "isPremium": false,
          "tags": ["graph", "dfs"]
        },
        {
          "title": "DFS",
          "slug": "dfs-graph",
          "difficulty": "Easy",
          "topic": "Graph",
          "platform": "GeeksForGeeks",
          "solveLink": "https://practice.geeksforgeeks.org/problems/depth-first-traversal-for-a-graph/1",
          "editorialLink": "https://takeuforward.org/data-structure/dfs/",
          "postLink": "https://takeuforward.org/data-structure/dfs/",
          "youtubeLink": "https://www.youtube.com/watch?v=uDWljP2PGmU",
          "isPremium": false,
          "tags": ["graph", "dfs"]
        },
        {
          "title": "BFS",
          "slug": "bfs-graph",
          "difficulty": "Easy",
          "topic": "Graph",
          "platform": "GeeksForGeeks",
          "solveLink": "https://practice.geeksforgeeks.org/problems/bfs-traversal-of-graph/1",
          "editorialLink": "https://takeuforward.org/data-structure/bfs/",
          "postLink": "https://takeuforward.org/data-structure/bfs/",
          "youtubeLink": "https://www.youtube.com/watch?v=UeE67iCK2lQ",
          "isPremium": false,
          "tags": ["graph", "bfs"]
        },
        {
          "title": "Detect Cycle in Undirected Graph using BFS",
          "slug": "detect-cycle-undirected-bfs",
          "difficulty": "Medium",
          "topic": "Graph",
          "platform": "GeeksForGeeks",
          "solveLink": "https://practice.geeksforgeeks.org/problems/detect-cycle-in-an-undirected-graph/1",
          "editorialLink": "https://takeuforward.org/data-structure/detect-cycle-in-undirected-graph-using-bfs/",
          "postLink": "https://takeuforward.org/data-structure/detect-cycle-in-undirected-graph-using-bfs/",
          "youtubeLink": "https://www.youtube.com/watch?v=BPlrALf1LDU",
          "isPremium": false,
          "tags": ["graph", "bfs", "cycle-detection"]
        },
        {
          "title": "Detect Cycle in Undirected Graph using DFS",
          "slug": "detect-cycle-undirected-dfs",
          "difficulty": "Medium",
          "topic": "Graph",
          "platform": "GeeksForGeeks",
          "solveLink": "https://practice.geeksforgeeks.org/problems/detect-cycle-in-an-undirected-graph/1",
          "editorialLink": "https://takeuforward.org/data-structure/detect-cycle-in-undirected-graph-using-dfs/",
          "postLink": "https://takeuforward.org/data-structure/detect-cycle-in-undirected-graph-using-dfs/",
          "youtubeLink": "https://www.youtube.com/watch?v=zQ3zgFypzX4",
          "isPremium": false,
          "tags": ["graph", "dfs", "cycle-detection"]
        },
        {
          "title": "Detect Cycle in Directed Graph using DFS",
          "slug": "detect-cycle-directed-dfs",
          "difficulty": "Medium",
          "topic": "Graph",
          "platform": "GeeksForGeeks",
          "solveLink": "https://practice.geeksforgeeks.org/problems/detect-cycle-in-a-directed-graph/1",
          "editorialLink": "https://takeuforward.org/data-structure/detect-cycle-in-directed-graph-using-dfs/",
          "postLink": "https://takeuforward.org/data-structure/detect-cycle-in-directed-graph-using-dfs/",
          "youtubeLink": "https://www.youtube.com/watch?v=9twcmtQj4DU",
          "isPremium": false,
          "tags": ["graph", "dfs", "cycle-detection"]
        },
        {
          "title": "Topological Sort using DFS",
          "slug": "topological-sort-dfs",
          "difficulty": "Medium",
          "topic": "Graph",
          "platform": "GeeksForGeeks",
          "solveLink": "https://practice.geeksforgeeks.org/problems/topological-sort/1",
          "editorialLink": "https://takeuforward.org/data-structure/topological-sort-dfs/",
          "postLink": "https://takeuforward.org/data-structure/topological-sort-dfs/",
          "youtubeLink": "https://www.youtube.com/watch?v=5lZ0iJMrUMk",
          "isPremium": false,
          "tags": ["graph", "dfs", "topological-sort"]
        },
        {
          "title": "Number of Islands",
          "slug": "number-of-islands",
          "difficulty": "Medium",
          "topic": "Graph",
          "platform": "LeetCode",
          "solveLink": "https://leetcode.com/problems/number-of-islands/",
          "editorialLink": "https://takeuforward.org/data-structure/number-of-islands/",
          "postLink": "https://takeuforward.org/data-structure/number-of-islands/",
          "youtubeLink": "https://www.youtube.com/watch?v=D0AFqdQA31U",
          "isPremium": false,
          "tags": ["graph", "dfs"]
        },
        {
          "title": "Bipartite Graph Check using BFS",
          "slug": "bipartite-graph-bfs",
          "difficulty": "Medium",
          "topic": "Graph",
          "platform": "LeetCode",
          "solveLink": "https://leetcode.com/problems/is-graph-bipartite/",
          "editorialLink": "https://takeuforward.org/data-structure/bipartite-graph-check-bfs/",
          "postLink": "https://takeuforward.org/data-structure/bipartite-graph-check-bfs/",
          "youtubeLink": "https://www.youtube.com/watch?v=-vu34sct1g8",
          "isPremium": false,
          "tags": ["graph", "bfs", "bipartite"]
        },
        {
          "title": "Dijkstra's Shortest Path",
          "slug": "dijkstras-shortest-path",
          "difficulty": "Hard",
          "topic": "Graph",
          "platform": "GeeksForGeeks",
          "solveLink": "https://practice.geeksforgeeks.org/problems/implementing-dijkstra-set-1-adjacency-matrix/1",
          "editorialLink": "https://takeuforward.org/data-structure/dijkstras-shortest-path/",
          "postLink": "https://takeuforward.org/data-structure/dijkstras-shortest-path/",
          "youtubeLink": "https://www.youtube.com/watch?v=V6H1qAeB-l4",
          "isPremium": false,
          "tags": ["graph", "shortest-path"]
        },
        {
          "title": "Bellman-Ford Algorithm",
          "slug": "bellman-ford",
          "difficulty": "Hard",
          "topic": "Graph",
          "platform": "GeeksForGeeks",
          "solveLink": "https://practice.geeksforgeeks.org/problems/distance-from-the-source-bellman-ford-algorithm/1",
          "editorialLink": "https://takeuforward.org/data-structure/bellman-ford/",
          "postLink": "https://takeuforward.org/data-structure/bellman-ford/",
          "youtubeLink": "https://www.youtube.com/watch?v=0vVofAhAYjc",
          "isPremium": false,
          "tags": ["graph", "shortest-path"]
        },
        {
          "title": "Floyd Warshall Algorithm",
          "slug": "floyd-warshall",
          "difficulty": "Hard",
          "topic": "Graph",
          "platform": "GeeksForGeeks",
          "solveLink": "https://practice.geeksforgeeks.org/problems/implementing-floyd-warshall-algorithm/0",
          "editorialLink": "https://takeuforward.org/data-structure/floyd-warshall/",
          "postLink": "https://takeuforward.org/data-structure/floyd-warshall/",
          "youtubeLink": "https://www.youtube.com/watch?v=nV_wOZnhbog",
          "isPremium": false,
          "tags": ["graph", "shortest-path"]
        },
        {
          "title": "MST using Prim's Algorithm",
          "slug": "mst-prims-algorithm",
          "difficulty": "Hard",
          "topic": "Graph",
          "platform": "GeeksForGeeks",
          "solveLink": "https://practice.geeksforgeeks.org/problems/minimum-spanning-tree/1",
          "editorialLink": "https://takeuforward.org/data-structure/prims-algorithm/",
          "postLink": "https://takeuforward.org/data-structure/prims-algorithm/",
          "youtubeLink": "https://www.youtube.com/watch?v=oP2-8ysT3QQ",
          "isPremium": false,
          "tags": ["graph", "mst"]
        },
        {
          "title": "MST using Kruskal's Algorithm",
          "slug": "mst-kruskals-algorithm",
          "difficulty": "Hard",
          "topic": "Graph",
          "platform": "GeeksForGeeks",
          "solveLink": "https://practice.geeksforgeeks.org/problems/minimum-spanning-tree/1",
          "editorialLink": "https://takeuforward.org/data-structure/kruskals-algorithm/",
          "postLink": "https://takeuforward.org/data-structure/kruskals-algorithm/",
          "youtubeLink": "https://www.youtube.com/watch?v=1KRmCzBl_mQ",
          "isPremium": false,
          "tags": ["graph", "mst"]
        }
      ]
    },
    {
      "title": "Dynamic Programming",
      "slug": "dynamic-programming",
      "order": 18,
      "problems": [
        {
          "title": "Maximum Product Subarray",
          "slug": "maximum-product-subarray",
          "difficulty": "Medium",
          "topic": "DP",
          "platform": "LeetCode",
          "solveLink": "https://leetcode.com/problems/maximum-product-subarray/",
          "editorialLink": "https://takeuforward.org/data-structure/maximum-product-subarray/",
          "postLink": "https://takeuforward.org/data-structure/maximum-product-subarray/",
          "youtubeLink": "https://www.youtube.com/watch?v=lXVy6YWFcRM",
          "isPremium": false,
          "tags": ["dp", "arrays"]
        },
        {
          "title": "Longest Increasing Subsequence",
          "slug": "longest-increasing-subsequence",
          "difficulty": "Medium",
          "topic": "DP",
          "platform": "LeetCode",
          "solveLink": "https://leetcode.com/problems/longest-increasing-subsequence/",
          "editorialLink": "https://takeuforward.org/data-structure/longest-increasing-subsequence/",
          "postLink": "https://takeuforward.org/data-structure/longest-increasing-subsequence/",
          "youtubeLink": "https://www.youtube.com/watch?v=ekcwMsSIzVc",
          "isPremium": false,
          "tags": ["dp", "binary-search"]
        },
        {
          "title": "Longest Common Subsequence",
          "slug": "longest-common-subsequence",
          "difficulty": "Medium",
          "topic": "DP",
          "platform": "LeetCode",
          "solveLink": "https://leetcode.com/problems/longest-common-subsequence/",
          "editorialLink": "https://takeuforward.org/data-structure/longest-common-subsequence/",
          "postLink": "https://takeuforward.org/data-structure/longest-common-subsequence/",
          "youtubeLink": "https://www.youtube.com/watch?v=NPZn9jBrX8U",
          "isPremium": false,
          "tags": ["dp", "strings"]
        },
        {
          "title": "0-1 Knapsack",
          "slug": "0-1-knapsack",
          "difficulty": "Hard",
          "topic": "DP",
          "platform": "GeeksForGeeks",
          "solveLink": "https://practice.geeksforgeeks.org/problems/0-1-knapsack-problem/0",
          "editorialLink": "https://takeuforward.org/data-structure/0-1-knapsack/",
          "postLink": "https://takeuforward.org/data-structure/0-1-knapsack/",
          "youtubeLink": "https://www.youtube.com/watch?v=GqOmJHQZivw",
          "isPremium": false,
          "tags": ["dp", "knapsack"]
        },
        {
          "title": "Edit Distance",
          "slug": "edit-distance",
          "difficulty": "Hard",
          "topic": "DP",
          "platform": "LeetCode",
          "solveLink": "https://leetcode.com/problems/edit-distance/",
          "editorialLink": "https://takeuforward.org/data-structure/edit-distance/",
          "postLink": "https://takeuforward.org/data-structure/edit-distance/",
          "youtubeLink": "https://www.youtube.com/watch?v=fJaKO8FbDdo",
          "isPremium": false,
          "tags": ["dp", "strings"]
        },
        {
          "title": "Maximum Sum Increasing Subsequence",
          "slug": "maximum-sum-increasing-subsequence",
          "difficulty": "Medium",
          "topic": "DP",
          "platform": "GeeksForGeeks",
          "solveLink": "https://practice.geeksforgeeks.org/problems/maximum-sum-increasing-subsequence/0",
          "editorialLink": "https://takeuforward.org/data-structure/maximum-sum-increasing-subsequence/",
          "postLink": "https://takeuforward.org/data-structure/maximum-sum-increasing-subsequence/",
          "youtubeLink": "https://www.youtube.com/watch?v=99ssGWhLPUE",
          "isPremium": false,
          "tags": ["dp", "lis"]
        },
        {
          "title": "Matrix Chain Multiplication",
          "slug": "matrix-chain-multiplication",
          "difficulty": "Hard",
          "topic": "DP",
          "platform": "GeeksForGeeks",
          "solveLink": "https://practice.geeksforgeeks.org/problems/matrix-chain-multiplication/0",
          "editorialLink": "https://takeuforward.org/data-structure/matrix-chain-multiplication/",
          "postLink": "https://takeuforward.org/data-structure/matrix-chain-multiplication/",
          "youtubeLink": "https://www.youtube.com/watch?v=vRVfmbCFW7Y",
          "isPremium": false,
          "tags": ["dp", "mcm"]
        }
      ]
    },
    {
      "title": "Dynamic Programming Part-II",
      "slug": "dynamic-programming-part-2",
      "order": 19,
      "problems": [
        {
          "title": "Minimum Path Sum in Grid",
          "slug": "min-path-sum-grid",
          "difficulty": "Medium",
          "topic": "DP",
          "platform": "LeetCode",
          "solveLink": "https://leetcode.com/problems/minimum-path-sum/",
          "editorialLink": "https://takeuforward.org/data-structure/minimum-path-sum-grid/",
          "postLink": "https://takeuforward.org/data-structure/minimum-path-sum-grid/",
          "youtubeLink": "https://www.youtube.com/watch?v=_rgTlyky1uQ",
          "isPremium": false,
          "tags": ["dp", "grid"]
        },
        {
          "title": "Coin Change II",
          "slug": "coin-change-2",
          "difficulty": "Medium",
          "topic": "DP",
          "platform": "LeetCode",
          "solveLink": "https://leetcode.com/problems/coin-change-2/",
          "editorialLink": "https://takeuforward.org/data-structure/coin-change-ii/",
          "postLink": "https://takeuforward.org/data-structure/coin-change-ii/",
          "youtubeLink": "https://www.youtube.com/watch?v=HgyouUi11zk",
          "isPremium": false,
          "tags": ["dp", "unbounded-knapsack"]
        },
        {
          "title": "Subset Sum Equal to Target",
          "slug": "subset-sum-equal-to-target",
          "difficulty": "Medium",
          "topic": "DP",
          "platform": "GeeksForGeeks",
          "solveLink": "https://practice.geeksforgeeks.org/problems/subset-sum-problem/0",
          "editorialLink": "https://takeuforward.org/data-structure/subset-sum-equal-to-target/",
          "postLink": "https://takeuforward.org/data-structure/subset-sum-equal-to-target/",
          "youtubeLink": "https://www.youtube.com/watch?v=fWX9xDmIzRI",
          "isPremium": false,
          "tags": ["dp", "knapsack"]
        },
        {
          "title": "Rod Cutting Problem",
          "slug": "rod-cutting",
          "difficulty": "Medium",
          "topic": "DP",
          "platform": "GeeksForGeeks",
          "solveLink": "https://practice.geeksforgeeks.org/problems/rod-cutting/0",
          "editorialLink": "https://takeuforward.org/data-structure/rod-cutting/",
          "postLink": "https://takeuforward.org/data-structure/rod-cutting/",
          "youtubeLink": "https://www.youtube.com/watch?v=SZqAQLjDsag",
          "isPremium": false,
          "tags": ["dp", "unbounded-knapsack"]
        },
        {
          "title": "Super Egg Drop",
          "slug": "super-egg-drop",
          "difficulty": "Hard",
          "topic": "DP",
          "platform": "LeetCode",
          "solveLink": "https://leetcode.com/problems/super-egg-drop/",
          "editorialLink": "https://takeuforward.org/data-structure/super-egg-drop/",
          "postLink": "https://takeuforward.org/data-structure/super-egg-drop/",
          "youtubeLink": "https://www.youtube.com/watch?v=3hcaVyX00_4",
          "isPremium": false,
          "tags": ["dp", "binary-search"]
        },
        {
          "title": "Word Break",
          "slug": "word-break-dp",
          "difficulty": "Medium",
          "topic": "DP",
          "platform": "LeetCode",
          "solveLink": "https://leetcode.com/problems/word-break/",
          "editorialLink": "https://takeuforward.org/data-structure/word-break-dp/",
          "postLink": "https://takeuforward.org/data-structure/word-break-dp/",
          "youtubeLink": "https://www.youtube.com/watch?v=th4OcGMlI54",
          "isPremium": false,
          "tags": ["dp", "strings"]
        },
        {
          "title": "Palindrome Partitioning MCM",
          "slug": "palindrome-partitioning-mcm",
          "difficulty": "Hard",
          "topic": "DP",
          "platform": "GeeksForGeeks",
          "solveLink": "https://practice.geeksforgeeks.org/problems/palindromic-patitioning/0",
          "editorialLink": "https://takeuforward.org/data-structure/palindrome-partitioning-mcm/",
          "postLink": "https://takeuforward.org/data-structure/palindrome-partitioning-mcm/",
          "youtubeLink": "https://www.youtube.com/watch?v=_H8V5hJUGd0",
          "isPremium": false,
          "tags": ["dp", "mcm"]
        },
        {
          "title": "Maximum Profit in Job Scheduling",
          "slug": "maximum-profit-job-scheduling",
          "difficulty": "Hard",
          "topic": "DP",
          "platform": "LeetCode",
          "solveLink": "https://leetcode.com/problems/maximum-profit-in-job-scheduling/",
          "editorialLink": "https://takeuforward.org/data-structure/maximum-profit-job-scheduling/",
          "postLink": "https://takeuforward.org/data-structure/maximum-profit-job-scheduling/",
          "youtubeLink": "https://www.youtube.com/watch?v=cr6Ip0J9izc",
          "isPremium": false,
          "tags": ["dp", "binary-search"]
        }
      ]
    },
    {
      "title": "Trie",
      "slug": "trie",
      "order": 20,
      "problems": [
        {
          "title": "Implement Trie",
          "slug": "implement-trie",
          "difficulty": "Medium",
          "topic": "Trie",
          "platform": "LeetCode",
          "solveLink": "https://leetcode.com/problems/implement-trie-prefix-tree/",
          "editorialLink": "https://takeuforward.org/data-structure/implement-trie/",
          "postLink": "https://takeuforward.org/data-structure/implement-trie/",
          "youtubeLink": "https://www.youtube.com/watch?v=dBGUmUQhjaM",
          "isPremium": false,
          "tags": ["trie", "design"]
        },
        {
          "title": "Implement Trie II (Advanced)",
          "slug": "implement-trie-2",
          "difficulty": "Hard",
          "topic": "Trie",
          "platform": "GeeksForGeeks",
          "solveLink": "https://practice.geeksforgeeks.org/problems/trie-insert-and-search/0",
          "editorialLink": "https://takeuforward.org/data-structure/implement-trie-ii/",
          "postLink": "https://takeuforward.org/data-structure/implement-trie-ii/",
          "youtubeLink": "https://www.youtube.com/watch?v=K5pcpkEMCN0",
          "isPremium": false,
          "tags": ["trie", "design"]
        },
        {
          "title": "Longest Word With All Prefixes",
          "slug": "longest-word-all-prefixes",
          "difficulty": "Medium",
          "topic": "Trie",
          "platform": "LeetCode",
          "solveLink": "https://leetcode.com/problems/longest-word-in-dictionary/",
          "editorialLink": "https://takeuforward.org/data-structure/longest-word-all-prefixes/",
          "postLink": "https://takeuforward.org/data-structure/longest-word-all-prefixes/",
          "youtubeLink": "https://www.youtube.com/watch?v=AWnBa91lThI",
          "isPremium": false,
          "tags": ["trie", "strings"]
        },
        {
          "title": "Count Distinct Substrings",
          "slug": "count-distinct-substrings",
          "difficulty": "Hard",
          "topic": "Trie",
          "platform": "GeeksForGeeks",
          "solveLink": "https://practice.geeksforgeeks.org/problems/count-of-distinct-substrings/1",
          "editorialLink": "https://takeuforward.org/data-structure/count-distinct-substrings/",
          "postLink": "https://takeuforward.org/data-structure/count-distinct-substrings/",
          "youtubeLink": "https://www.youtube.com/watch?v=RV0QeTyHZxo",
          "isPremium": false,
          "tags": ["trie", "strings"]
        },
        {
          "title": "Power Set",
          "slug": "power-set",
          "difficulty": "Easy",
          "topic": "Trie",
          "platform": "LeetCode",
          "solveLink": "https://leetcode.com/problems/subsets/",
          "editorialLink": "https://takeuforward.org/data-structure/power-set/",
          "postLink": "https://takeuforward.org/data-structure/power-set/",
          "youtubeLink": "https://www.youtube.com/watch?v=b7AYbpM5YrE",
          "isPremium": false,
          "tags": ["backtracking", "bit-manipulation"]
        },
        {
          "title": "Maximum XOR of Two Numbers",
          "slug": "max-xor-of-two-numbers",
          "difficulty": "Hard",
          "topic": "Trie",
          "platform": "LeetCode",
          "solveLink": "https://leetcode.com/problems/maximum-xor-of-two-numbers-in-an-array/",
          "editorialLink": "https://takeuforward.org/data-structure/maximum-xor-of-two-numbers/",
          "postLink": "https://takeuforward.org/data-structure/maximum-xor-of-two-numbers/",
          "youtubeLink": "https://www.youtube.com/watch?v=EIhAwfHubE8",
          "isPremium": false,
          "tags": ["trie", "bit-manipulation"]
        },
        {
          "title": "Maximum XOR With an Element From Array",
          "slug": "max-xor-with-element-from-array",
          "difficulty": "Hard",
          "topic": "Trie",
          "platform": "LeetCode",
          "solveLink": "https://leetcode.com/problems/maximum-xor-with-an-element-from-array/",
          "editorialLink": "https://takeuforward.org/data-structure/maximum-xor-with-an-element-from-array/",
          "postLink": "https://takeuforward.org/data-structure/maximum-xor-with-an-element-from-array/",
          "youtubeLink": "https://www.youtube.com/watch?v=Q8LhG9Pi5KM",
          "isPremium": false,
          "tags": ["trie", "bit-manipulation"]
        }
      ]
    }
  ]
}
